setup.py
gux_dsnd_distributions/Binomialdistribution.py
gux_dsnd_distributions/Gaussiandistribution.py
gux_dsnd_distributions/Generaldistribution.py
gux_dsnd_distributions/__init__.py
gux_dsnd_distributions.egg-info/PKG-INFO
gux_dsnd_distributions.egg-info/SOURCES.txt
gux_dsnd_distributions.egg-info/dependency_links.txt
gux_dsnd_distributions.egg-info/not-zip-safe
gux_dsnd_distributions.egg-info/top_level.txt