Metadata-Version: 1.0
Name: gux-dsnd-distributions
Version: 1.0
Summary: Gaussian and Binomial distributions
Home-page: UNKNOWN
Author: Gabriel Bezerra
Author-email: gabrielsrbezerra@gmail.com
License: UNKNOWN
Platform: UNKNOWN
